upscayl/__init__.py
upscayl/upscayl.py
upscayl/bin/Linux/upscayl-bin
upscayl/bin/Windows/upscayl-bin.exe
upscayl/bin/Windows/vcomp140.dll
upscayl/bin/Windows/vcomp140d.dll
upscayl-0.0.0a1.dist-info/METADATA
upscayl-0.0.0a1.dist-info/WHEEL
upscayl-0.0.0a1.dist-info/RECORD
