Metadata-Version: 2.3
Name: upscayl
Version: 0.0.0a1
Summary: A small example package
Project-URL: Homepage, https://github.com/HumXC/upscayl-python
Project-URL: Bug Tracker, https://github.com/HumXC/upscayl-python/issues
Author-email: HumXC <Hum-XC@outlook.com>
Classifier: License :: OSI Approved :: MIT License
Classifier: Programming Language :: Python :: 3
Requires-Python: >=3.7
Requires-Dist: pillow
